docscanner/__init__.py
docscanner/docscanner.py
docscanner/data/Style Guide Phrases.csv
doc_scanner-0.5.dist-info/METADATA
doc_scanner-0.5.dist-info/WHEEL
doc_scanner-0.5.dist-info/entry_points.txt
doc_scanner-0.5.dist-info/top_level.txt
doc_scanner-0.5.dist-info/RECORD
