Metadata-Version: 2.1
Name: doc-scanner
Version: 0.5
Summary: A script to scan HTML documents for forbidden phrases stored in a CSV.
Home-page: https://github.com/marcinwalczak2
Author: Marcin Walczak
Classifier: Programming Language :: Python :: 3
Classifier: License :: OSI Approved :: MIT License
Classifier: Operating System :: OS Independent
Requires-Python: >=3.6
Requires-Dist: beautifulsoup4
Requires-Dist: requests
Requires-Dist: pandas
Requires-Dist: setuptools
